{
    "energy_uncertainty": 1.0,
    "genetic_algorithm": "NEDLER_MEAD",
    "skip_print": false,
    "energy_unit": "kcal/mol",
    "energies": {
        "106": -8372.9300,
        "104": -8372.8200,
        "006": -8372.7500
    },
    "spectra_data": [
        {
            "type": "VCD",
            "file": "VCD_EXP",
            "mirroring_option": 0.3,
            "hwhm": 6.0,
            "interval": [950, 1850],
            "scaling_factors": [[900, 1600, 1.020], [1600 , 1900 , 1.000]],
            "optimise": true
        },
        {
            "file": "IR_EXP",
            "type": "IR",
            "mirroring_option": 0.3,
            "hwhm": 6.0,
            "interval": [950, 1850],
            "scaling_factors": [[900, 1600, 1.020], [1600 , 1900 , 1.000]],
            "optimise": true
        }
    ],
    "comment": "(1-tanimoto(vcd, VCD_EXP))**2 + (1-tanimoto(ir, IR_EXP))**2"
 }
